crint/__init__.py
crint/constants.py
crint-0.1.1.dist-info/METADATA
crint-0.1.1.dist-info/WHEEL
crint-0.1.1.dist-info/top_level.txt
crint-0.1.1.dist-info/RECORD
